pytest_bug/__init__.py
pytest_bug/__version__.py
pytest_bug/hooks.py
pytest_bug/plugin.py
pytest_bug-1.6.0.dist-info/licenses/LICENSE
pytest_bug-1.6.0.dist-info/METADATA
pytest_bug-1.6.0.dist-info/WHEEL
pytest_bug-1.6.0.dist-info/entry_points.txt
pytest_bug-1.6.0.dist-info/top_level.txt
pytest_bug-1.6.0.dist-info/RECORD
